jobextractor/__init__.py
jobextractor/extractor.py
jobextractor/formatters.py
jobextractor/models.py
jobextractor-0.1.0.dist-info/licenses/LICENSE
jobextractor-0.1.0.dist-info/METADATA
jobextractor-0.1.0.dist-info/WHEEL
jobextractor-0.1.0.dist-info/top_level.txt
jobextractor-0.1.0.dist-info/RECORD
