Metadata-Version: 2.4
Name: jobextractor
Version: 0.1.0
Summary: Professional job description extraction using multiple LLM providers
Home-page: https://github.com/oelbourki/JobExtractor
Author: Otmane El Bourki
Author-email: Otmane El Bourki <otmane.elbourki@gmail.com>
License: MIT
Project-URL: Homepage, https://github.com/oelbourki/JobExtractor
Project-URL: Documentation, https://github.com/oelbourki/JobExtractor#readme
Project-URL: Repository, https://github.com/oelbourki/JobExtractor
Project-URL: Issues, https://github.com/oelbourki/JobExtractor/issues
Keywords: job-extraction,llm,nlp,structured-data,litellm,openai,anthropic,gemini,ollama
Classifier: Development Status :: 4 - Beta
Classifier: Intended Audience :: Developers
Classifier: License :: OSI Approved :: MIT License
Classifier: Programming Language :: Python :: 3
Classifier: Programming Language :: Python :: 3.8
Classifier: Programming Language :: Python :: 3.9
Classifier: Programming Language :: Python :: 3.10
Classifier: Programming Language :: Python :: 3.11
Classifier: Programming Language :: Python :: 3.12
Classifier: Topic :: Software Development :: Libraries :: Python Modules
Classifier: Topic :: Text Processing :: Linguistic
Classifier: Topic :: Scientific/Engineering :: Artificial Intelligence
Requires-Python: >=3.8
License-File: LICENSE
Requires-Dist: pydantic>=2.0.0
Requires-Dist: litellm>=1.0.0
Provides-Extra: dev
Requires-Dist: pytest>=7.0.0; extra == "dev"
Requires-Dist: pytest-cov>=4.0.0; extra == "dev"
Requires-Dist: black>=23.0.0; extra == "dev"
Requires-Dist: ruff>=0.1.0; extra == "dev"
Requires-Dist: mypy>=1.0.0; extra == "dev"
Requires-Dist: build>=0.10.0; extra == "dev"
Requires-Dist: twine>=4.0.0; extra == "dev"
Provides-Extra: docs
Requires-Dist: sphinx>=5.0.0; extra == "docs"
Requires-Dist: sphinx-rtd-theme>=1.0.0; extra == "docs"
Dynamic: author
Dynamic: home-page
Dynamic: license-file
Dynamic: requires-python
